.gitignore
README.txt
bootstrap.py
buildout.cfg
jenkins
jenkins.bat
setup.py
docs/Makefile
docs/api.txt
docs/changes.txt
docs/conf.py
docs/copy.txt
docs/description.txt
docs/development.txt
docs/display.txt
docs/filter.txt
docs/index.txt
docs/installation.txt
docs/license.txt
docs/make.bat
docs/margins.txt
docs/save.txt
docs/styles.txt
docs/view.txt
xlutils/__init__.py
xlutils/copy.py
xlutils/display.py
xlutils/filter.py
xlutils/license.txt
xlutils/margins.py
xlutils/save.py
xlutils/styles.py
xlutils/version.txt
xlutils/view.py
xlutils.egg-info/PKG-INFO
xlutils.egg-info/SOURCES.txt
xlutils.egg-info/dependency_links.txt
xlutils.egg-info/entry_points.txt
xlutils.egg-info/not-zip-safe
xlutils.egg-info/requires.txt
xlutils.egg-info/top_level.txt
xlutils/tests/__init__.py
xlutils/tests/date.xls
xlutils/tests/fixtures.py
xlutils/tests/ragged.xls
xlutils/tests/test.xls
xlutils/tests/test_copy.py
xlutils/tests/test_docs.py
xlutils/tests/test_filter.py
xlutils/tests/test_save.py
xlutils/tests/test_styles.py
xlutils/tests/test_view.py
xlutils/tests/testall.xls
xlutils/tests/testnoformatting.xls