Metadata-Version: 1.0
Name: xlutils
Version: 1.7.0
Summary: Utilities for working with Excel files that require both xlrd and xlwt
Home-page: http://www.python-excel.org
Author: Chris Withers
Author-email: chris@simplistix.co.uk
License: MIT
Keywords: excel xls xlrd xlwt
Platform: UNKNOWN
Classifier: Development Status :: 6 - Mature
Classifier: Intended Audience :: Developers
Classifier: License :: OSI Approved :: MIT License
Classifier: Topic :: Office/Business :: Financial :: Spreadsheet
